mozmlops/.DS_Store
mozmlops/__init__.py
mozmlops/cloud_storage_api_client.py
mozmlops/templates/.metaflow/TemplateFlow/1719590776600065/_meta/_self.json
mozmlops/templates/.metaflow/TemplateFlow/1719590776600065/_parameters/0/0.DONE.lock
mozmlops/templates/.metaflow/TemplateFlow/1719590776600065/_parameters/0/0.attempt.json
mozmlops/templates/.metaflow/TemplateFlow/1719590776600065/_parameters/0/0.data.json
mozmlops/templates/.metaflow/TemplateFlow/1719590776600065/_parameters/0/_meta/0_artifact__foreach_stack.json
mozmlops/templates/.metaflow/TemplateFlow/1719590776600065/_parameters/0/_meta/0_artifact__graph_info.json
mozmlops/templates/.metaflow/TemplateFlow/1719590776600065/_parameters/0/_meta/0_artifact__success.json
mozmlops/templates/.metaflow/TemplateFlow/1719590776600065/_parameters/0/_meta/0_artifact__task_ok.json
mozmlops/templates/.metaflow/TemplateFlow/1719590776600065/_parameters/0/_meta/0_artifact__transition.json
mozmlops/templates/.metaflow/TemplateFlow/1719590776600065/_parameters/0/_meta/0_artifact_example_config.json
mozmlops/templates/.metaflow/TemplateFlow/1719590776600065/_parameters/0/_meta/0_artifact_name.json
mozmlops/templates/.metaflow/TemplateFlow/1719590776600065/_parameters/0/_meta/0_artifact_offline_wandb.json
mozmlops/templates/.metaflow/TemplateFlow/1719590776600065/_parameters/0/_meta/_self.json
mozmlops/templates/.metaflow/TemplateFlow/1719590776600065/_parameters/0/_meta/sysmeta_attempt-done_1719590776606.json
mozmlops/templates/.metaflow/TemplateFlow/1719590776600065/_parameters/0/_meta/sysmeta_metaflow_version_1719590776603.json
mozmlops/templates/.metaflow/TemplateFlow/1719590776600065/_parameters/0/_meta/sysmeta_python_version_1719590776603.json
mozmlops/templates/.metaflow/TemplateFlow/1719590776600065/_parameters/0/_meta/sysmeta_runtime_1719590776603.json
mozmlops/templates/.metaflow/TemplateFlow/1719590776600065/_parameters/0/_meta/sysmeta_user_1719590776603.json
mozmlops-0.1.4.dist-info/LICENSE
mozmlops-0.1.4.dist-info/METADATA
mozmlops-0.1.4.dist-info/WHEEL
mozmlops-0.1.4.dist-info/RECORD
