Metadata-Version: 2.1
Name: mozmlops
Version: 0.1.4
Summary: A package for getting your models into production
License: MPL-2.0
Author: Mozilla MLOps
Requires-Python: >=3.10,<4.0
Classifier: License :: OSI Approved
Classifier: Programming Language :: Python :: 3
Classifier: Programming Language :: Python :: 3.10
Classifier: Programming Language :: Python :: 3.11
Classifier: Programming Language :: Python :: 3.12
Requires-Dist: google-api-core (>=2.19.0,<3.0.0)
Requires-Dist: google-cloud-storage (>=2.16.0,<3.0.0)
Requires-Dist: numpy (<2.0.0)
Requires-Dist: outerbounds[gcp] (>=0.3.77,<0.4.0)
Requires-Dist: ruff (>=0.4.3,<0.5.0)
Requires-Dist: wandb (>=0.17.3,<0.18.0)
